{
  "organization": {
    "id": 203310501,
    "ein": 203310501,
    "name": "Biobricks Foundation Incorporated",
    "careofname": "% BRIAN SCHULZ",
    "address": "77 VAN NESS AVE",
    "city": "San Francisco",
    "state": "CA",
    "zipcode": "94102-6041",
    "exemption_number": 0,
    "subsection_code": 3,
    "affiliation_code": 3,
    "classification_codes": "2100",
    "ruling_date": "2006-05-01",
    "deductibility_code": 1,
    "foundation_code": 15,
    "activity_codes": "000000000",
    "organization_code": 1,
    "exempt_organization_status_code": 1,
    "tax_period": "2023-07-01",
    "asset_code": 3,
    "income_code": 1,
    "filing_requirement_code": 2,
    "pf_filing_requirement_code": 0,
    "accounting_period": 7,
    "asset_amount": 65647,
    "income_amount": 363,
    "revenue_amount": 363,
    "ntee_code": "U05",
    "sort_name": null,
    "created_at": "2023-05-09T20:35:49.625Z",
    "updated_at": "2025-08-14T19:32:48.012Z",
    "data_source": "current_2025_08_14",
    "have_extracts": null,
    "have_pdfs": null,
    "latest_object_id": "202410529349201041"
  },
  "filings_with_data": [
    {
      "tax_prd": 202307,
      "tax_prd_yr": 2023,
      "formtype": 1,
      "pdf_url": "https://projects.propublica.org/nonprofits/download-filing?path=download990pdf_03_2024_prefixes_01-20%2F203310501_202307_990EZ_2024030522308410.pdf",
      "updated": "2025-08-05T16:11:47.805Z",
      "totrevenue": 363,
      "totfuncexpns": 92369,
      "totassetsend": 65647,
      "totliabend": 30804,
      "pct_compnsatncurrofcr": -0.001,
      "subseccd": 3,
      "totcntrbs": 334,
      "prgmservrev": 0,
      "duesassesmnts": 0,
      "othrinvstinc": 29,
      "grsamtsalesastothr": 0,
      "basisalesexpnsothr": 0,
      "gnsaleofastothr": 0,
      "grsincgaming": 0,
      "grsrevnuefndrsng": 0,
      "direxpns": 0,
      "netincfndrsng": 0,
      "grsalesminusret": 0,
      "costgoodsold": 0,
      "grsprft": 0,
      "othrevnue": 0,
      "totrevnue": 363,
      "totexpns": 92369,
      "totexcessyr": -92006,
      "othrchgsnetassetfnd": 0,
      "totnetassetsend": 34843,
      "unrelbusincd": null,
      "initiationfee": 0,
      "grspublicrcpts": 0,
      "nonpfrea": "7",
      "gftgrntrcvd170": 3944,
      "txrevnuelevied170": 0,
      "srvcsval170": 0,
      "grsinc170": 1413,
      "grsrcptsrelatd170": 0,
      "totgftgrntrcvd509": 0,
      "grsrcptsadmiss509": 0,
      "txrevnuelevied509": 0,
      "srvcsval509": 0,
      "subtotsuppinc509": 0,
      "totsupp509": 0,
      "ein": 203310501
    },
    {
      "tax_prd": 202207,
      "tax_prd_yr": 2022,
      "formtype": 1,
      "pdf_url": null,
      "updated": "2024-08-28T20:21:49.368Z",
      "totrevenue": 243,
      "totfuncexpns": 122874,
      "totassetsend": 126849,
      "totliabend": 0,
      "pct_compnsatncurrofcr": -0.001,
      "subseccd": 3,
      "totcntrbs": 29,
      "prgmservrev": 0,
      "duesassesmnts": 0,
      "othrinvstinc": 66,
      "grsamtsalesastothr": 0,
      "basisalesexpnsothr": 0,
      "gnsaleofastothr": 0,
      "grsincgaming": 0,
      "grsrevnuefndrsng": 0,
      "direxpns": 0,
      "netincfndrsng": 0,
      "grsalesminusret": 0,
      "costgoodsold": 0,
      "grsprft": 0,
      "othrevnue": 148,
      "totrevnue": 243,
      "totexpns": 122874,
      "totexcessyr": -122631,
      "othrchgsnetassetfnd": 0,
      "totnetassetsend": 126849,
      "unrelbusincd": null,
      "initiationfee": 0,
      "grspublicrcpts": 0,
      "nonpfrea": "7",
      "gftgrntrcvd170": 1806859,
      "txrevnuelevied170": 0,
      "srvcsval170": 0,
      "grsinc170": 1841,
      "grsrcptsrelatd170": 0,
      "totgftgrntrcvd509": 0,
      "grsrcptsadmiss509": 0,
      "txrevnuelevied509": 0,
      "srvcsval509": 0,
      "subtotsuppinc509": 0,
      "totsupp509": 0,
      "ein": 203310501
    },
    {
      "tax_prd": 202107,
      "tax_prd_yr": 2021,
      "formtype": 1,
      "pdf_url": "https://projects.propublica.org/nonprofits/download-filing?path=download990pdf_07_2022_prefixes_01-22%2F203310501_202107_990EZ_2022071120196490.pdf",
      "updated": "2023-08-07T19:49:48.973Z",
      "totrevenue": 31341,
      "totfuncexpns": 343727,
      "totassetsend": 251737,
      "totliabend": 2257,
      "pct_compnsatncurrofcr": -0.001,
      "subseccd": 3,
      "totcntrbs": 1227,
      "prgmservrev": 0,
      "duesassesmnts": 0,
      "othrinvstinc": 189,
      "grsamtsalesastothr": 0,
      "basisalesexpnsothr": 0,
      "gnsaleofastothr": 0,
      "grsincgaming": 0,
      "grsrevnuefndrsng": 0,
      "direxpns": 0,
      "netincfndrsng": 0,
      "grsalesminusret": 0,
      "costgoodsold": 0,
      "grsprft": 0,
      "othrevnue": 29925,
      "totrevnue": 31341,
      "totexpns": 343727,
      "totexcessyr": -312386,
      "othrchgsnetassetfnd": 0,
      "totnetassetsend": 249480,
      "unrelbusincd": null,
      "initiationfee": 0,
      "grspublicrcpts": 0,
      "nonpfrea": "07",
      "gftgrntrcvd170": 3325175,
      "txrevnuelevied170": 0,
      "srvcsval170": 0,
      "grsinc170": 2152,
      "grsrcptsrelatd170": 0,
      "totgftgrntrcvd509": 0,
      "grsrcptsadmiss509": 0,
      "txrevnuelevied509": 0,
      "srvcsval509": 0,
      "subtotsuppinc509": 0,
      "totsupp509": 0,
      "ein": 203310501
    },
    {
      "tax_prd": 202007,
      "tax_prd_yr": 2020,
      "formtype": 0,
      "pdf_url": null,
      "updated": "2022-07-01T20:27:22.325Z",
      "totrevenue": 1851,
      "totfuncexpns": 540721,
      "totassetsend": 593966,
      "totliabend": 32101,
      "pct_compnsatncurrofcr": 0.0,
      "tax_pd": null,
      "subseccd": 3,
      "unrelbusinccd": "N",
      "initiationfees": 0,
      "grsrcptspublicuse": 0,
      "grsincmembers": 0,
      "grsincother": 0,
      "totcntrbgfts": 1310,
      "totprgmrevnue": 0,
      "invstmntinc": 541,
      "txexmptbndsproceeds": 0,
      "royaltsinc": 0,
      "grsrntsreal": 0,
      "grsrntsprsnl": 0,
      "rntlexpnsreal": 0,
      "rntlexpnsprsnl": 0,
      "rntlincreal": 0,
      "rntlincprsnl": 0,
      "netrntlinc": 0,
      "grsalesecur": 0,
      "grsalesothr": 0,
      "cstbasisecur": 0,
      "cstbasisothr": 0,
      "gnlsecur": 0,
      "gnlsothr": 0,
      "netgnls": 0,
      "grsincfndrsng": 0,
      "lessdirfndrsng": 0,
      "netincfndrsng": 0,
      "grsincgaming": 0,
      "lessdirgaming": 0,
      "netincgaming": 0,
      "grsalesinvent": 0,
      "lesscstofgoods": 0,
      "netincsales": 0,
      "miscrevtot11e": 0,
      "compnsatncurrofcr": 0,
      "othrsalwages": 67272,
      "payrolltx": 5950,
      "profndraising": 0,
      "txexmptbndsend": 0,
      "secrdmrtgsend": 29925,
      "unsecurednotesend": 0,
      "retainedearnend": 0,
      "totnetassetend": 561865,
      "nonpfrea": "7",
      "gftgrntsrcvd170": 4636207,
      "txrevnuelevied170": 0,
      "srvcsval170": 0,
      "grsinc170": 2254,
      "grsrcptsrelated170": 0,
      "totgftgrntrcvd509": 0,
      "grsrcptsadmissn509": 0,
      "txrevnuelevied509": 0,
      "srvcsval509": 0,
      "subtotsuppinc509": 0,
      "totsupp509": 0,
      "ein": 203310501
    },
    {
      "tax_prd": 201907,
      "tax_prd_yr": 2019,
      "formtype": 0,
      "pdf_url": "https://projects.propublica.org/nonprofits/download-filing?path=01_2021_prefixes_20-22%2F203310501_201907_990_2021012117619424.pdf",
      "updated": "2021-08-30T18:56:06.518Z",
      "totrevenue": 1631,
      "totfuncexpns": 744073,
      "totassetsend": 1160007,
      "totliabend": 59272,
      "pct_compnsatncurrofcr": 0.0,
      "tax_pd": null,
      "subseccd": 3,
      "unrelbusinccd": "N",
      "initiationfees": 0,
      "grsrcptspublicuse": 0,
      "grsincmembers": 0,
      "grsincother": 0,
      "totcntrbgfts": 1043,
      "totprgmrevnue": 0,
      "invstmntinc": 588,
      "txexmptbndsproceeds": 0,
      "royaltsinc": 0,
      "grsrntsreal": 0,
      "grsrntsprsnl": 0,
      "rntlexpnsreal": 0,
      "rntlexpnsprsnl": 0,
      "rntlincreal": 0,
      "rntlincprsnl": 0,
      "netrntlinc": 0,
      "grsalesecur": 0,
      "grsalesothr": 0,
      "cstbasisecur": 0,
      "cstbasisothr": 0,
      "gnlsecur": 0,
      "gnlsothr": 0,
      "netgnls": 0,
      "grsincfndrsng": 0,
      "lessdirfndrsng": 0,
      "netincfndrsng": 0,
      "grsincgaming": 0,
      "lessdirgaming": 0,
      "netincgaming": 0,
      "grsalesinvent": 0,
      "lesscstofgoods": 0,
      "netincsales": 0,
      "miscrevtot11e": 0,
      "compnsatncurrofcr": 0,
      "othrsalwages": 212174,
      "payrolltx": 15504,
      "profndraising": 0,
      "txexmptbndsend": 0,
      "secrdmrtgsend": 0,
      "unsecurednotesend": 0,
      "retainedearnend": 0,
      "totnetassetend": 1100735,
      "nonpfrea": "07",
      "gftgrntsrcvd170": 5961604,
      "txrevnuelevied170": 0,
      "srvcsval170": 0,
      "grsinc170": 1828,
      "grsrcptsrelated170": 0,
      "totgftgrntrcvd509": 0,
      "grsrcptsadmissn509": 0,
      "txrevnuelevied509": 0,
      "srvcsval509": 0,
      "subtotsuppinc509": 0,
      "totsupp509": 0,
      "ein": 203310501
    },
    {
      "tax_prd": 201807,
      "tax_prd_yr": 2018,
      "formtype": 0,
      "pdf_url": "https://projects.propublica.org/nonprofits/download-filing?path=07_2019_prefixes_16-20%2F203310501_201807_990_2019070516464178.pdf",
      "updated": "2021-08-30T18:37:15.940Z",
      "totrevenue": 1803707,
      "totfuncexpns": 1090943,
      "totassetsend": 1958091,
      "totliabend": 114914,
      "pct_compnsatncurrofcr": 0.0,
      "tax_pd": null,
      "subseccd": 3,
      "unrelbusinccd": "N",
      "initiationfees": 0,
      "grsrcptspublicuse": 0,
      "grsincmembers": 0,
      "grsincother": 0,
      "totcntrbgfts": 1803250,
      "totprgmrevnue": 0,
      "invstmntinc": 457,
      "txexmptbndsproceeds": 0,
      "royaltsinc": 0,
      "grsrntsreal": 0,
      "grsrntsprsnl": 0,
      "rntlexpnsreal": 0,
      "rntlexpnsprsnl": 0,
      "rntlincreal": 0,
      "rntlincprsnl": 0,
      "netrntlinc": 0,
      "grsalesecur": 0,
      "grsalesothr": 0,
      "cstbasisecur": 0,
      "cstbasisothr": 0,
      "gnlsecur": 0,
      "gnlsothr": 0,
      "netgnls": 0,
      "grsincfndrsng": 0,
      "lessdirfndrsng": 0,
      "netincfndrsng": 0,
      "grsincgaming": 0,
      "lessdirgaming": 0,
      "netincgaming": 0,
      "grsalesinvent": 0,
      "lesscstofgoods": 0,
      "netincsales": 0,
      "miscrevtot11e": 0,
      "compnsatncurrofcr": 0,
      "othrsalwages": 429381,
      "payrolltx": 28351,
      "profndraising": 0,
      "txexmptbndsend": 0,
      "secrdmrtgsend": 0,
      "unsecurednotesend": 0,
      "retainedearnend": 0,
      "totnetassetend": 1843177,
      "nonpfrea": "07",
      "gftgrntsrcvd170": 6050117,
      "txrevnuelevied170": 0,
      "srvcsval170": 0,
      "grsinc170": 1301,
      "grsrcptsrelated170": 0,
      "totgftgrntrcvd509": 0,
      "grsrcptsadmissn509": 0,
      "txrevnuelevied509": 0,
      "srvcsval509": 0,
      "subtotsuppinc509": 0,
      "totsupp509": 0,
      "ein": 203310501
    },
    {
      "tax_prd": 201707,
      "tax_prd_yr": 2017,
      "formtype": 0,
      "pdf_url": "https://projects.propublica.org/nonprofits/download-filing?path=09_2018_prefixes_20-20%2F203310501_201707_990_2018091015670522.pdf",
      "updated": "2019-10-15T18:27:47.697Z",
      "totrevenue": 1518722,
      "totfuncexpns": 1417089,
      "totassetsend": 1462199,
      "totliabend": 331786,
      "pct_compnsatncurrofcr": 0.0,
      "tax_pd": null,
      "subseccd": 3,
      "unrelbusinccd": "N",
      "initiationfees": 0,
      "grsrcptspublicuse": 0,
      "grsincmembers": 0,
      "grsincother": 0,
      "totcntrbgfts": 1518345,
      "totprgmrevnue": 0,
      "invstmntinc": 377,
      "txexmptbndsproceeds": 0,
      "royaltsinc": 0,
      "grsrntsreal": 0,
      "grsrntsprsnl": 0,
      "rntlexpnsreal": 0,
      "rntlexpnsprsnl": 0,
      "rntlincreal": 0,
      "rntlincprsnl": 0,
      "netrntlinc": 0,
      "grsalesecur": 0,
      "grsalesothr": 0,
      "cstbasisecur": 0,
      "cstbasisothr": 0,
      "gnlsecur": 0,
      "gnlsothr": 0,
      "netgnls": 0,
      "grsincfndrsng": 0,
      "lessdirfndrsng": 0,
      "netincfndrsng": 0,
      "grsincgaming": 0,
      "lessdirgaming": 0,
      "netincgaming": 0,
      "grsalesinvent": 0,
      "lesscstofgoods": 0,
      "netincsales": 0,
      "miscrevtot11e": 0,
      "compnsatncurrofcr": 0,
      "othrsalwages": 462394,
      "payrolltx": 31217,
      "profndraising": 0,
      "txexmptbndsend": 0,
      "secrdmrtgsend": 0,
      "unsecurednotesend": 0,
      "retainedearnend": 0,
      "totnetassetend": 1130413,
      "nonpfrea": "7",
      "gftgrntsrcvd170": 4398159,
      "txrevnuelevied170": 0,
      "srvcsval170": 0,
      "grsinc170": 1011,
      "grsrcptsrelated170": 0,
      "totgftgrntrcvd509": 0,
      "grsrcptsadmissn509": 0,
      "txrevnuelevied509": 0,
      "srvcsval509": 0,
      "subtotsuppinc509": 0,
      "totsupp509": 0,
      "ein": 203310501
    },
    {
      "tax_prd": 201607,
      "tax_prd_yr": 2016,
      "formtype": 0,
      "pdf_url": "https://projects.propublica.org/nonprofits/download-filing?path=IRS%2F203310501_201607_990_2017091214723434.pdf",
      "updated": "2018-12-10T23:10:09.014Z",
      "totrevenue": 1312550,
      "totfuncexpns": 1149772,
      "totassetsend": 2394555,
      "totliabend": 1365775,
      "pct_compnsatncurrofcr": 0.0,
      "tax_pd": null,
      "subseccd": 3,
      "unrelbusinccd": "N",
      "initiationfees": 0,
      "grsrcptspublicuse": 0,
      "grsincmembers": 0,
      "grsincother": 0,
      "totcntrbgfts": 1312259,
      "totprgmrevnue": 0,
      "invstmntinc": 291,
      "txexmptbndsproceeds": 0,
      "royaltsinc": 0,
      "grsrntsreal": 0,
      "grsrntsprsnl": 0,
      "rntlexpnsreal": 0,
      "rntlexpnsprsnl": 0,
      "rntlincreal": 0,
      "rntlincprsnl": 0,
      "netrntlinc": 0,
      "grsalesecur": 0,
      "grsalesothr": 0,
      "cstbasisecur": 0,
      "cstbasisothr": 0,
      "gnlsecur": 0,
      "gnlsothr": 0,
      "netgnls": 0,
      "grsincfndrsng": 0,
      "lessdirfndrsng": 0,
      "netincfndrsng": 0,
      "grsincgaming": 0,
      "lessdirgaming": 0,
      "netincgaming": 0,
      "grsalesinvent": 0,
      "lesscstofgoods": 0,
      "netincsales": 0,
      "miscrevtot11e": 0,
      "compnsatncurrofcr": 0,
      "othrsalwages": 292917,
      "payrolltx": 23034,
      "profndraising": 0,
      "txexmptbndsend": 0,
      "secrdmrtgsend": 0,
      "unsecurednotesend": 0,
      "retainedearnend": 1028780,
      "totnetassetend": 1028780,
      "nonpfrea": "7",
      "gftgrntsrcvd170": 3067254,
      "txrevnuelevied170": 0,
      "srvcsval170": 0,
      "grsinc170": 858,
      "grsrcptsrelated170": 0,
      "totgftgrntrcvd509": 0,
      "grsrcptsadmissn509": 0,
      "txrevnuelevied509": 0,
      "srvcsval509": 0,
      "subtotsuppinc509": 0,
      "totsupp509": 0,
      "ein": 203310501
    },
    {
      "tax_prd": 201507,
      "tax_prd_yr": 2015,
      "formtype": 0,
      "pdf_url": "https://projects.propublica.org/nonprofits/download-filing?path=2017_01_EO%2F20-3310501_990_201507.pdf",
      "updated": "2017-06-30T00:35:51.240Z",
      "totrevenue": 1327534,
      "totfuncexpns": 596641,
      "totassetsend": 882955,
      "totliabend": 16953,
      "pct_compnsatncurrofcr": 0.0,
      "tax_pd": null,
      "subseccd": 3,
      "unrelbusinccd": "N",
      "initiationfees": 0,
      "grsrcptspublicuse": 0,
      "grsincmembers": 0,
      "grsincother": 0,
      "totcntrbgfts": 1326707,
      "totprgmrevnue": 0,
      "invstmntinc": 115,
      "txexmptbndsproceeds": 0,
      "royaltsinc": 0,
      "grsrntsreal": 0,
      "grsrntsprsnl": 0,
      "rntlexpnsreal": 0,
      "rntlexpnsprsnl": 0,
      "rntlincreal": 0,
      "rntlincprsnl": 0,
      "netrntlinc": 0,
      "grsalesecur": 0,
      "grsalesothr": 0,
      "cstbasisecur": 0,
      "cstbasisothr": 0,
      "gnlsecur": 0,
      "gnlsothr": 0,
      "netgnls": 0,
      "grsincfndrsng": 0,
      "lessdirfndrsng": 0,
      "netincfndrsng": 0,
      "grsincgaming": 0,
      "lessdirgaming": 0,
      "netincgaming": 0,
      "grsalesinvent": 0,
      "lesscstofgoods": 0,
      "netincsales": 0,
      "miscrevtot11e": 712,
      "compnsatncurrofcr": 0,
      "othrsalwages": 0,
      "payrolltx": 0,
      "profndraising": 0,
      "txexmptbndsend": 0,
      "secrdmrtgsend": 0,
      "unsecurednotesend": 0,
      "retainedearnend": 866002,
      "totnetassetend": 866002,
      "nonpfrea": "7",
      "gftgrntsrcvd170": 2476217,
      "txrevnuelevied170": 0,
      "srvcsval170": 0,
      "grsinc170": 672,
      "grsrcptsrelated170": 0,
      "totgftgrntrcvd509": 0,
      "grsrcptsadmissn509": 0,
      "txrevnuelevied509": 0,
      "srvcsval509": 0,
      "subtotsuppinc509": 0,
      "totsupp509": 0,
      "ein": 203310501
    },
    {
      "tax_prd": 201407,
      "tax_prd_yr": 2014,
      "formtype": 0,
      "pdf_url": "https://projects.propublica.org/nonprofits/download-filing?path=2015_09_EO%2F20-3310501_990_201407.pdf",
      "updated": "2017-06-30T00:22:39.883Z",
      "totrevenue": 89617,
      "totfuncexpns": 275735,
      "totassetsend": 151336,
      "totliabend": 16227,
      "pct_compnsatncurrofcr": 0.0,
      "tax_pd": null,
      "subseccd": 3,
      "unrelbusinccd": "N",
      "initiationfees": 0,
      "grsrcptspublicuse": 0,
      "grsincmembers": 0,
      "grsincother": 0,
      "totcntrbgfts": 89556,
      "totprgmrevnue": 0,
      "invstmntinc": 61,
      "txexmptbndsproceeds": 0,
      "royaltsinc": 0,
      "grsrntsreal": 0,
      "grsrntsprsnl": 0,
      "rntlexpnsreal": 0,
      "rntlexpnsprsnl": 0,
      "rntlincreal": 0,
      "rntlincprsnl": 0,
      "netrntlinc": 0,
      "grsalesecur": 0,
      "grsalesothr": 0,
      "cstbasisecur": 0,
      "cstbasisothr": 0,
      "gnlsecur": 0,
      "gnlsothr": 0,
      "netgnls": 0,
      "grsincfndrsng": 0,
      "lessdirfndrsng": 0,
      "netincfndrsng": 0,
      "grsincgaming": 0,
      "lessdirgaming": 0,
      "netincgaming": 0,
      "grsalesinvent": 0,
      "lesscstofgoods": 0,
      "netincsales": 0,
      "miscrevtot11e": 0,
      "compnsatncurrofcr": 19975,
      "othrsalwages": 0,
      "payrolltx": 651,
      "profndraising": 1079,
      "txexmptbndsend": 0,
      "secrdmrtgsend": 0,
      "unsecurednotesend": 0,
      "retainedearnend": 135109,
      "totnetassetend": 135109,
      "nonpfrea": "7",
      "gftgrntsrcvd170": 1305510,
      "txrevnuelevied170": 0,
      "srvcsval170": 0,
      "grsinc170": 557,
      "grsrcptsrelated170": 0,
      "totgftgrntrcvd509": 0,
      "grsrcptsadmissn509": 0,
      "txrevnuelevied509": 0,
      "srvcsval509": 0,
      "subtotsuppinc509": 0,
      "totsupp509": 0,
      "ein": 203310501
    },
    {
      "tax_prd": 201307,
      "tax_prd_yr": 2013,
      "formtype": 0,
      "pdf_url": "https://projects.propublica.org/nonprofits/download-filing?path=2015_09_EO%2F20-3310501_990_201307.pdf",
      "updated": "2017-06-30T00:22:02.045Z",
      "totrevenue": 611131,
      "totfuncexpns": 524086,
      "totassetsend": 370590,
      "totliabend": 49363,
      "pct_compnsatncurrofcr": 0.0,
      "tax_pd": null,
      "subseccd": 3,
      "unrelbusinccd": "N",
      "initiationfees": 0,
      "grsrcptspublicuse": 0,
      "grsincmembers": 0,
      "grsincother": 0,
      "totcntrbgfts": 151292,
      "totprgmrevnue": 459475,
      "invstmntinc": 364,
      "txexmptbndsproceeds": 0,
      "royaltsinc": 0,
      "grsrntsreal": 0,
      "grsrntsprsnl": 0,
      "rntlexpnsreal": 0,
      "rntlexpnsprsnl": 0,
      "rntlincreal": 0,
      "rntlincprsnl": 0,
      "netrntlinc": 0,
      "grsalesecur": 0,
      "grsalesothr": 0,
      "cstbasisecur": 0,
      "cstbasisothr": 0,
      "gnlsecur": 0,
      "gnlsothr": 0,
      "netgnls": 0,
      "grsincfndrsng": 0,
      "lessdirfndrsng": 0,
      "netincfndrsng": 0,
      "grsincgaming": 0,
      "lessdirgaming": 0,
      "netincgaming": 0,
      "grsalesinvent": 0,
      "lesscstofgoods": 0,
      "netincsales": 0,
      "miscrevtot11e": 0,
      "compnsatncurrofcr": 149500,
      "othrsalwages": 0,
      "payrolltx": 9232,
      "profndraising": 3459,
      "txexmptbndsend": 0,
      "secrdmrtgsend": 0,
      "unsecurednotesend": 0,
      "retainedearnend": 321227,
      "totnetassetend": 321227,
      "nonpfrea": "7",
      "gftgrntsrcvd170": 1460415,
      "txrevnuelevied170": 0,
      "srvcsval170": 0,
      "grsinc170": 496,
      "grsrcptsrelated170": 0,
      "totgftgrntrcvd509": 0,
      "grsrcptsadmissn509": 0,
      "txrevnuelevied509": 0,
      "srvcsval509": 0,
      "subtotsuppinc509": 0,
      "totsupp509": 0,
      "ein": 203310501
    },
    {
      "tax_prd": 201207,
      "tax_prd_yr": 2012,
      "formtype": 0,
      "pdf_url": "https://projects.propublica.org/nonprofits/download-filing?path=2013_03_EO%2F20-3310501_990_201207.pdf",
      "updated": "2017-06-29T23:50:47.465Z",
      "totrevenue": 237929,
      "totfuncexpns": 321932,
      "totassetsend": 288403,
      "totliabend": 4250,
      "pct_compnsatncurrofcr": 0.0,
      "tax_pd": null,
      "subseccd": 3,
      "unrelbusinccd": "N",
      "initiationfees": 0,
      "grsrcptspublicuse": 0,
      "grsincmembers": 0,
      "grsincother": 0,
      "totcntrbgfts": 37440,
      "totprgmrevnue": 199200,
      "invstmntinc": 289,
      "txexmptbndsproceeds": 0,
      "royaltsinc": 0,
      "grsrntsreal": 0,
      "grsrntsprsnl": 0,
      "rntlexpnsreal": 0,
      "rntlexpnsprsnl": 0,
      "rntlincreal": 0,
      "rntlincprsnl": 0,
      "netrntlinc": 0,
      "grsalesecur": 0,
      "grsalesothr": 0,
      "cstbasisecur": 0,
      "cstbasisothr": 0,
      "gnlsecur": 0,
      "gnlsothr": 0,
      "netgnls": 0,
      "grsincfndrsng": 0,
      "lessdirfndrsng": 0,
      "netincfndrsng": 0,
      "grsincgaming": 0,
      "lessdirgaming": 0,
      "netincgaming": 0,
      "grsalesinvent": 0,
      "lesscstofgoods": 0,
      "netincsales": 0,
      "miscrevtot11e": 1000,
      "compnsatncurrofcr": 146364,
      "othrsalwages": 19994,
      "payrolltx": 12864,
      "profndraising": 0,
      "txexmptbndsend": 0,
      "secrdmrtgsend": 0,
      "unsecurednotesend": 0,
      "retainedearnend": 284153,
      "totnetassetend": 284153,
      "nonpfrea": "7",
      "gftgrntsrcvd170": 1470698,
      "txrevnuelevied170": 0,
      "srvcsval170": 0,
      "grsinc170": 393,
      "grsrcptsrelated170": 0,
      "totgftgrntrcvd509": 0,
      "grsrcptsadmissn509": 0,
      "txrevnuelevied509": 0,
      "srvcsval509": 0,
      "subtotsuppinc509": 0,
      "totsupp509": 0,
      "ein": 203310501
    },
    {
      "tax_prd": 201107,
      "tax_prd_yr": 2011,
      "formtype": 0,
      "pdf_url": "https://projects.propublica.org/nonprofits/download-filing?path=2012_04_EO%2F20-3310501_990_201107.pdf",
      "updated": "2017-06-29T23:36:16.515Z",
      "totrevenue": 911097,
      "totfuncexpns": 654790,
      "totassetsend": 453441,
      "totliabend": 85285,
      "pct_compnsatncurrofcr": 0.0,
      "tax_pd": null,
      "subseccd": 3,
      "unrelbusinccd": "N",
      "initiationfees": 0,
      "grsrcptspublicuse": 0,
      "grsincmembers": 0,
      "grsincother": 0,
      "totcntrbgfts": 721222,
      "totprgmrevnue": 189182,
      "invstmntinc": 105,
      "txexmptbndsproceeds": 0,
      "royaltsinc": 0,
      "grsrntsreal": 0,
      "grsrntsprsnl": 0,
      "rntlexpnsreal": 0,
      "rntlexpnsprsnl": 0,
      "rntlincreal": 0,
      "rntlincprsnl": 0,
      "netrntlinc": 0,
      "grsalesecur": 0,
      "grsalesothr": 0,
      "cstbasisecur": 0,
      "cstbasisothr": 0,
      "gnlsecur": 0,
      "gnlsothr": 0,
      "netgnls": 0,
      "grsincfndrsng": 0,
      "lessdirfndrsng": 0,
      "netincfndrsng": 0,
      "grsincgaming": 0,
      "lessdirgaming": 0,
      "netincgaming": 0,
      "grsalesinvent": 0,
      "lesscstofgoods": 0,
      "netincsales": 0,
      "miscrevtot11e": 588,
      "compnsatncurrofcr": 103480,
      "othrsalwages": 0,
      "payrolltx": 0,
      "profndraising": 0,
      "txexmptbndsend": 0,
      "secrdmrtgsend": 0,
      "unsecurednotesend": 0,
      "retainedearnend": 368156,
      "totnetassetend": 368156,
      "nonpfrea": "7",
      "gftgrntsrcvd170": 1238708,
      "txrevnuelevied170": 0,
      "srvcsval170": 0,
      "grsinc170": 105,
      "grsrcptsrelated170": 189770,
      "totgftgrntrcvd509": 0,
      "grsrcptsadmissn509": 0,
      "txrevnuelevied509": 0,
      "srvcsval509": 0,
      "subtotsuppinc509": 0,
      "totsupp509": 0,
      "ein": 203310501
    }
  ],
  "filings_without_data": [
    {
      "tax_prd": 201007,
      "tax_prd_yr": 2010,
      "formtype": 1,
      "formtype_str": "990EZ",
      "pdf_url": "https://projects.propublica.org/nonprofits/download-filing?path=2010_10_EO%2F20-3310501_990EZ_201007.pdf"
    },
    {
      "tax_prd": 200907,
      "tax_prd_yr": 2009,
      "formtype": 1,
      "formtype_str": "990EZ",
      "pdf_url": "https://projects.propublica.org/nonprofits/download-filing?path=2010_06_EO%2F20-3310501_990EZ_200907.pdf"
    },
    {
      "tax_prd": 200807,
      "tax_prd_yr": 2008,
      "formtype": 0,
      "formtype_str": "990",
      "pdf_url": "https://projects.propublica.org/nonprofits/download-filing?path=2009_06_EO%2F20-3310501_990_200807.pdf"
    }
  ],
  "data_source": "ProPublica Nonprofit Explorer API: https://projects.propublica.org/nonprofits/api/\nIRS Exempt Organizations Business Master File Extract (EO BMF): https://www.irs.gov/charities-non-profits/exempt-organizations-business-master-file-extract-eo-bmf\nIRS Annual Extract of Tax-Exempt Organization Financial Data: https://www.irs.gov/uac/soi-tax-stats-annual-extract-of-tax-exempt-organization-financial-data",
  "api_version": 2
}